geotoolkit/__init__.py
geotoolkit-0.2.1.dist-info/METADATA
geotoolkit-0.2.1.dist-info/WHEEL
geotoolkit-0.2.1.dist-info/license.md
geotoolkit-0.2.1.dist-info/top_level.txt
geotoolkit-0.2.1.dist-info/RECORD
